{
  "types":[
    {
      "name":"com.hotpot.common.entity.BaseUser"
    },
    {
      "name":"java.lang.Exception"
    },
    {
      "name":"java.lang.Integer"
    },
    {
      "name":"java.lang.Long"
    },
    {
      "name":"java.lang.Number"
    },
    {
      "name":"java.lang.RuntimeException"
    },
    {
      "name":"java.lang.StackTraceElement"
    },
    {
      "name":"java.lang.StackTraceElement[]"
    },
    {
      "name":"java.lang.String"
    },
    {
      "name":"java.lang.String$CaseInsensitiveComparator"
    },
    {
      "name":"java.lang.Throwable"
    },
    {
      "name":"java.net.URL"
    },
    {
      "name":"java.time.Instant"
    },
    {
      "name":"java.time.Ser"
    },
    {
      "name":"java.util.ArrayList"
    },
    {
      "name":"java.util.Collections$EmptyList"
    },
    {
      "name":"java.util.Collections$UnmodifiableCollection"
    },
    {
      "name":"java.util.Collections$UnmodifiableList"
    },
    {
      "name":"java.util.Collections$UnmodifiableMap"
    },
    {
      "name":"java.util.Collections$UnmodifiableRandomAccessList"
    },
    {
      "name":"java.util.Collections$UnmodifiableSet"
    },
    {
      "name":"java.util.HashMap"
    },
    {
      "name":"java.util.HashSet"
    },
    {
      "name":"java.util.LinkedHashMap"
    },
    {
      "name":"java.util.LinkedHashSet"
    },
    {
      "name":"java.util.Locale"
    },
    {
      "name":"java.util.TreeMap"
    },
    {
      "name":"java.util.TreeSet"
    },
    {
      "name":"org.springframework.security.authentication.AbstractAuthenticationToken"
    },
    {
      "name":"org.springframework.security.authentication.BadCredentialsException"
    },
    {
      "name":"org.springframework.security.authentication.UsernamePasswordAuthenticationToken"
    },
    {
      "name":"org.springframework.security.core.AuthenticationException"
    },
    {
      "name":"org.springframework.security.core.authority.SimpleGrantedAuthority"
    },
    {
      "name":"org.springframework.security.core.context.SecurityContextImpl"
    },
    {
      "name":"org.springframework.security.core.userdetails.User"
    },
    {
      "name":"org.springframework.security.core.userdetails.User$AuthorityComparator"
    },
    {
      "name":"org.springframework.security.oauth2.client.authentication.OAuth2AuthenticationToken"
    },
    {
      "name":"org.springframework.security.oauth2.core.AbstractOAuth2Token"
    },
    {
      "name":"org.springframework.security.oauth2.core.AuthorizationGrantType"
    },
    {
      "name":"org.springframework.security.oauth2.core.endpoint.OAuth2AuthorizationRequest"
    },
    {
      "name":"org.springframework.security.oauth2.core.endpoint.OAuth2AuthorizationResponseType"
    },
    {
      "name":"org.springframework.security.oauth2.core.oidc.OidcIdToken"
    },
    {
      "name":"org.springframework.security.oauth2.core.oidc.OidcUserInfo"
    },
    {
      "name":"org.springframework.security.oauth2.core.oidc.user.DefaultOidcUser"
    },
    {
      "name":"org.springframework.security.oauth2.core.user.DefaultOAuth2User"
    },
    {
      "name":"org.springframework.security.web.authentication.WebAuthenticationDetails"
    },
    {
      "name":"org.springframework.security.web.csrf.DefaultCsrfToken"
    },
    {
      "name":"org.springframework.security.web.savedrequest.DefaultSavedRequest"
    },
    {
      "name":"org.springframework.security.web.savedrequest.SavedCookie"
    }
  ],
  "lambdaCapturingTypes":[
  ],
  "proxies":[
  ]
}
